dsplayer/__init__.py
dsplayer/__pycache__/__init__.cpython-310.pyc
dsplayer/engines/bandcamp.py
dsplayer/engines/soundcloud.py
dsplayer/engines/ytmusic.py
dsplayer/engines/__pycache__/bandcamp.cpython-310.pyc
dsplayer/engines/__pycache__/soundcloud.cpython-310.pyc
dsplayer/engines/__pycache__/ytmusic.cpython-310.pyc
dsplayer/engines_system/__init__.py
dsplayer/engines_system/engine_interface.py
dsplayer/engines_system/__pycache__/__init__.cpython-310.pyc
dsplayer/engines_system/__pycache__/engine_interface.cpython-310.pyc
dsplayer/player_system/__init__.py
dsplayer/player_system/player.py
dsplayer/player_system/queue.py
dsplayer/player_system/__pycache__/__init__.cpython-310.pyc
dsplayer/player_system/__pycache__/player.cpython-310.pyc
dsplayer/player_system/__pycache__/queue.cpython-310.pyc
dsplayer/plugin_system/__init__.py
dsplayer/plugin_system/plugin_interface.py
dsplayer/plugin_system/plugin_loader.py
dsplayer/plugin_system/query_plugin.py
dsplayer/plugin_system/test_addon_plugin.py
dsplayer/plugin_system/__pycache__/__init__.cpython-310.pyc
dsplayer/plugin_system/__pycache__/plugin_interface.cpython-310.pyc
dsplayer/plugin_system/__pycache__/plugin_loader.cpython-310.pyc
dsplayer/plugin_system/__pycache__/query_plugin.cpython-310.pyc
dsplayer/utils/__init__.py
dsplayer/utils/compat.py
dsplayer/utils/debug.py
dsplayer/utils/events.py
dsplayer/utils/lib_exceptions.py
dsplayer/utils/user_agent.py
dsplayer/utils/__pycache__/__init__.cpython-310.pyc
dsplayer/utils/__pycache__/compat.cpython-310.pyc
dsplayer/utils/__pycache__/debug.cpython-310.pyc
dsplayer/utils/__pycache__/events.cpython-310.pyc
dsplayer/utils/__pycache__/lib_exceptions.cpython-310.pyc
dsplayer/utils/__pycache__/user_agent.cpython-310.pyc
dsplayer-2.2.0.dist-info/LICENSE
dsplayer-2.2.0.dist-info/METADATA
dsplayer-2.2.0.dist-info/WHEEL
dsplayer-2.2.0.dist-info/top_level.txt
dsplayer-2.2.0.dist-info/RECORD
