Metadata-Version: 2.1
Name: dsplayer
Version: 2.2.0
Summary: Music player for Discord
Home-page: https://github.com/FlacSy/dsplayer
Author: FlacSy
Author-email: flacsy.x@gmail.com
Requires-Python: >=3.10.0
License-File: LICENSE
Requires-Dist: requests
Requires-Dist: bs4
Requires-Dist: colorama
Requires-Dist: selenium
Requires-Dist: webdriver-manager
Requires-Dist: yt-dlp
Requires-Dist: PyNaCl
